automate_analysis/__init__.py
automate_analysis/automate_analysis.py
automate_analysis-0.0.2.dist-info/METADATA
automate_analysis-0.0.2.dist-info/WHEEL
automate_analysis-0.0.2.dist-info/top_level.txt
automate_analysis-0.0.2.dist-info/RECORD
